kodexa_widget/__init__.py
kodexa_widget/_version.py
kodexa_widget/kodexa.py
kodexa_widget/static/010c1aeee3c6d1cbb1d5761d80353823.woff2
kodexa_widget/static/037d830416495def72b7881024c14b7b.woff2
kodexa_widget/static/0509ab09c1b0d2200a4135803c91d6ce.woff2
kodexa_widget/static/1.index.js
kodexa_widget/static/1.index.js.map
kodexa_widget/static/19b7a0adfdd4f808b53af7e2ce2ad4e5.woff2
kodexa_widget/static/2.index.js
kodexa_widget/static/2.index.js.map
kodexa_widget/static/210a7c781f5a354a0e4985656ab456d9.woff
kodexa_widget/static/285467176f7fe6bb6a9c6873b3dad2cc.woff2
kodexa_widget/static/29b882f018fa6fe75fd338aaae6235b8.woff
kodexa_widget/static/2d0a0d8f5f173be15a67aa084db94fe6.eot
kodexa_widget/static/510dec37fa69fba39593e01a469ee018.woff2
kodexa_widget/static/55536c8e9e9a532651e3cf374f290ea3.woff2
kodexa_widget/static/5d4aeb4e5f5ef754e307d7ffaef688bd.woff2
kodexa_widget/static/6232f43d15b0e7a0bf0fe82e295bdd06.woff2
kodexa_widget/static/7b770d6c53423deb1a8e49d3c9175184.woff2
kodexa_widget/static/846d1890aee87fde5d8ced8eba360c3a.woff
kodexa_widget/static/8c2ade503b34e31430d6c98aa29a52a3.woff
kodexa_widget/static/9680d5a0c32d2fd084e07bbc4c8b2923.woff
kodexa_widget/static/96c476804d7a788cc1c05351b287ee41.eot
kodexa_widget/static/987b84570ea69ee660455b8d5e91f5f1.woff2
kodexa_widget/static/a1471d1d6431c893582a5f6a250db3f9.woff
kodexa_widget/static/b4917be25082eb793b5363f2fdb5f282.woff
kodexa_widget/static/bafb105baeb22d965c70fe52ba6b49d9.woff
kodexa_widget/static/bc833e725c137257c2c42a789845d82f.woff
kodexa_widget/static/cf6613d1adf490972c557a8e318e0868.woff
kodexa_widget/static/d0066537ab6a4c6f8285a5aeb3ba5f09.woff2
kodexa_widget/static/d69924b98acd849cdeba9fbff3f88ea6.woff2
kodexa_widget/static/d704bb3d579b7d5e40880c75705c8a71.woff
kodexa_widget/static/d8bcbe724fd6f4ba44d0ee6a2675890f.woff2
kodexa_widget/static/da4ea5cdfca6b3baab285741f5ccb59f.ttf
kodexa_widget/static/de8b7431b74642e830af4d4f4b513ec9.woff
kodexa_widget/static/e9dbbe8a693dd275c16d32feb101f1c1.woff
kodexa_widget-4.0.10.dist-info/METADATA
kodexa_widget-4.0.10.dist-info/WHEEL
kodexa_widget-4.0.10.dist-info/top_level.txt
kodexa_widget-4.0.10.dist-info/RECORD
