Metadata-Version: 2.1
Name: kodexa-widget
Version: 4.0.10
Summary: A Jupyter Widget for Kodexa
Home-page: https://github.com/kodexa-ai/kodexa-widget
Author: Kodexa
Author-email: support@kodexa.com
License: UNKNOWN
Keywords: ipython,jupyter,widgets,kodexa
Platform: UNKNOWN
Classifier: Development Status :: 4 - Beta
Classifier: Framework :: IPython
Classifier: Intended Audience :: Developers
Classifier: Intended Audience :: Science/Research
Classifier: Topic :: Multimedia :: Graphics
Classifier: Programming Language :: Python :: 3.7
Requires-Dist: ipyvue (<2,>=1.3.2)
Requires-Dist: kodexa (>=2.0.0)
Requires-Dist: ipywidgets (>=7.5.1)
